ucbreq/__init__.py
ucbreq/py.typed
ucbreq-2.0.5.dist-info/LICENSE
ucbreq-2.0.5.dist-info/WHEEL
ucbreq-2.0.5.dist-info/METADATA
ucbreq-2.0.5.dist-info/RECORD
