Metadata-Version: 2.1
Name: ucbreq
Version: 2.0.5
Summary: Simple format for serialization, similar to CSV.  Not useful for most general use.
Author-email: "Taylor C. Richberger" <taylor.richberger@procern.com>
Requires-Python: >= 3.5, < 4
Classifier: Development Status :: 5 - Production/Stable
Classifier: Intended Audience :: Developers
Classifier: License :: OSI Approved :: MIT License
Classifier: Operating System :: OS Independent
Classifier: Programming Language :: Python :: 3
Classifier: Programming Language :: Python :: 3.5
Classifier: Topic :: Software Development :: Libraries :: Python Modules
Classifier: Topic :: Software Development :: Libraries
Project-URL: documentation, https://ucbreq.readthedocs.io/
Project-URL: repository, https://github.com/ProCern/ucbreq
